consisTent/__init__.py
consisTent/cache/__init__.py
consisTent/cache/base_cache.py
consisTent/cache/chroma_cache.py
consisTent/validators/__init__.py
consisTent/validators/base_validator.py
consisTent/validators/syntactic_validators.py
consisTent/validators/semantic_validators/__init__.py
consisTent/validators/semantic_validators/consistency_validator.py
consisTent/validators/semantic_validators/facts_validator.py
consisTent/validators/semantic_validators/labels_validator.py
consisTent/validators/semantic_validators/request_response_matching_validator.py
consistent-0.0.10.dist-info/LICENSE
consistent-0.0.10.dist-info/METADATA
consistent-0.0.10.dist-info/WHEEL
consistent-0.0.10.dist-info/top_level.txt
consistent-0.0.10.dist-info/RECORD
