Metadata-Version: 2.1
Name: consistent
Version: 0.0.10
Summary: Make sure AI model outputs are consistent
License: MIT License
Project-URL: Homepage, https://github.com/drorivry/consistent
Keywords: OpenAI,LLM,GPT,Cohere
Classifier: License :: OSI Approved :: MIT License
Classifier: Programming Language :: Python
Classifier: Programming Language :: Python :: 3
Requires-Python: >=3.8
License-File: LICENSE
Requires-Dist: chromadb
Requires-Dist: openai
Requires-Dist: js2py
Requires-Dist: jsonschema
Requires-Dist: langchain
Requires-Dist: tomli ; python_version < "3.11"
Provides-Extra: dev
Requires-Dist: black ; extra == 'dev'
Requires-Dist: bumpver ; extra == 'dev'
Requires-Dist: isort ; extra == 'dev'
Requires-Dist: pip-tools ; extra == 'dev'
Requires-Dist: pytest ; extra == 'dev'
Requires-Dist: pre-commit ; extra == 'dev'
Requires-Dist: pyflakes ; extra == 'dev'
